llama_index/llms/bedrock/__init__.py
llama_index/llms/bedrock/base.py
llama_index/llms/bedrock/llama_utils.py
llama_index/llms/bedrock/utils.py
llama_index_llms_bedrock-0.4.2.dist-info/METADATA
llama_index_llms_bedrock-0.4.2.dist-info/WHEEL
llama_index_llms_bedrock-0.4.2.dist-info/licenses/LICENSE
llama_index_llms_bedrock-0.4.2.dist-info/RECORD
