Metadata-Version: 2.4
Name: llama-index-llms-bedrock
Version: 0.4.2
Summary: llama-index llms bedrock integration
Author-email: Your Name <you@example.com>
License-Expression: MIT
License-File: LICENSE
Requires-Python: <4.0,>=3.9
Requires-Dist: boto3<2,>=1.34.26
Requires-Dist: llama-index-core<0.15,>=0.13.0
Requires-Dist: llama-index-llms-anthropic<0.9,>=0.8.0
